[{"id":1,"speaker":1,"speaker_name":"TonyHLP","is_super":1,"belong_class":1,"content":"Hello World","thread":1,"emoji":null,"img_url":null,"date":1561182751,"type":"text","file_url":null,"file_name":null},{"id":2,"speaker":1,"speaker_name":"TonyHLP","is_super":1,"belong_class":1,"content":"Hello World","thread":1,"emoji":0,"img_url":null,"date":1561186810,"type":"text","file_url":null,"file_name":null},{"id":3,"speaker":1,"speaker_name":"TonyHLP","is_super":1,"belong_class":1,"content":"Test Image ???","thread":1,"emoji":0,"img_url":"https:\/\/dnp4pehkvoo6n.cloudfront.net\/680b6d08a4f63bea218b37a64dc8d962\/as\/5ccaea1daaf36.jpg","date":1561186868,"type":"text","file_url":null,"file_name":null},{"id":4,"speaker":1,"speaker_name":"TonyHLP","is_super":1,"belong_class":1,"content":"Sending Test","thread":1,"emoji":0,"img_url":null,"date":1561193748,"type":"text","file_url":null,"file_name":null},{"id":5,"speaker":1,"speaker_name":"TonyHLP","is_super":1,"belong_class":1,"content":"Sending another test","thread":1,"emoji":0,"img_url":null,"date":1561193852,"type":"text","file_url":null,"file_name":null},{"id":6,"speaker":1,"speaker_name":"TonyHLP","is_super":1,"belong_class":1,"content":"Sending again","thread":1,"emoji":0,"img_url":null,"date":1561193882,"type":"text","file_url":null,"file_name":null},{"id":7,"speaker":1,"speaker_name":"TonyHLP","is_super":1,"belong_class":1,"content":"1","thread":1,"emoji":0,"img_url":null,"date":1561194158,"type":"text","file_url":null,"file_name":null},{"id":8,"speaker":1,"speaker_name":"TonyHLP","is_super":1,"belong_class":1,"content":"2","thread":1,"emoji":0,"img_url":null,"date":1561194160,"type":"text","file_url":null,"file_name":null},{"id":9,"speaker":1,"speaker_name":"TonyHLP","is_super":1,"belong_class":1,"content":"3","thread":1,"emoji":0,"img_url":null,"date":1561194161,"type":"text","file_url":null,"file_name":null},{"id":10,"speaker":1,"speaker_name":"TonyHLP","is_super":1,"belong_class":1,"content":"4","thread":1,"emoji":0,"img_url":null,"date":1561194163,"type":"text","file_url":null,"file_name":null},{"id":11,"speaker":1,"speaker_name":"TonyHLP","is_super":1,"belong_class":1,"content":null,"thread":1,"emoji":0,"img_url":null,"date":1561197988,"type":"file","file_url":"https:\/\/static.ouorz.com\/1561197987838.pdf","file_name":"1561197987838.pdf"},{"id":12,"speaker":1,"speaker_name":"TonyHLP","is_super":1,"belong_class":1,"content":"null","thread":1,"emoji":0,"img_url":"https:\/\/static.ouorz.com\/1561200737996.jpg","date":1561200740,"type":"text","file_url":null,"file_name":null},{"id":13,"speaker":1,"speaker_name":"TonyHLP","is_super":1,"belong_class":1,"content":"Hello World","thread":2,"emoji":0,"img_url":null,"date":1561201127,"type":"text","file_url":null,"file_name":null},{"id":14,"speaker":1,"speaker_name":"TonyHLP","is_super":1,"belong_class":1,"content":"Test Again","thread":1,"emoji":0,"img_url":null,"date":1561201404,"type":"text","file_url":null,"file_name":null},{"id":15,"speaker":1,"speaker_name":"TonyHLP","is_super":1,"belong_class":1,"content":"Hello World??","thread":2,"emoji":0,"img_url":null,"date":1561201415,"type":"text","file_url":null,"file_name":null},{"id":16,"speaker":1,"speaker_name":"TonyHLP","is_super":1,"belong_class":1,"content":"Ok, test again","thread":2,"emoji":0,"img_url":null,"date":1561201497,"type":"text","file_url":null,"file_name":null},{"id":17,"speaker":1,"speaker_name":"TonyHLP","is_super":1,"belong_class":1,"content":"Let's test","thread":2,"emoji":0,"img_url":null,"date":1561201554,"type":"text","file_url":null,"file_name":null},{"id":18,"speaker":1,"speaker_name":"TonyHLP","is_super":1,"belong_class":1,"content":"Let's test","thread":2,"emoji":0,"img_url":null,"date":1561201603,"type":"text","file_url":null,"file_name":null},{"id":19,"speaker":1,"speaker_name":"TonyHLP","is_super":1,"belong_class":1,"content":"Let's test again!","thread":2,"emoji":0,"img_url":null,"date":1561201615,"type":"text","file_url":null,"file_name":null},{"id":20,"speaker":1,"speaker_name":"TonyHLP","is_super":1,"belong_class":1,"content":"\u8bf6\uff1f\n\u80fd\u6362\u884c\u5417\uff1f","thread":1,"emoji":0,"img_url":null,"date":1561202270,"type":"text","file_url":null,"file_name":null},{"id":21,"speaker":1,"speaker_name":"TonyHLP","is_super":1,"belong_class":1,"content":"Fixed!","thread":1,"emoji":0,"img_url":null,"date":1561202456,"type":"text","file_url":null,"file_name":null},{"id":22,"speaker":1,"speaker_name":"TonyHLP","is_super":1,"belong_class":1,"content":"Test Multi-peers","thread":1,"emoji":0,"img_url":null,"date":1561204149,"type":"text","file_url":null,"file_name":null},{"id":23,"speaker":1,"speaker_name":"TonyHLP","is_super":1,"belong_class":1,"content":"Test!!","thread":1,"emoji":0,"img_url":null,"date":1561204485,"type":"text","file_url":null,"file_name":null},{"id":24,"speaker":1,"speaker_name":"TonyHLP","is_super":1,"belong_class":1,"content":null,"thread":1,"emoji":0,"img_url":null,"date":1561204967,"type":"file","file_url":"https:\/\/static.ouorz.com\/1561204966891.md","file_name":"1561204966891.md"},{"id":25,"speaker":1,"speaker_name":"TonyHLP","is_super":1,"belong_class":1,"content":null,"thread":1,"emoji":0,"img_url":null,"date":1561205098,"type":"file","file_url":"https:\/\/static.ouorz.com\/1561205098143.md","file_name":"Product Name.md"},{"id":26,"speaker":1,"speaker_name":"TonyHLP","is_super":1,"belong_class":1,"content":null,"thread":1,"emoji":0,"img_url":null,"date":1561205272,"type":"file","file_url":"https:\/\/static.ouorz.com\/1561205272010.key","file_name":"RavenClub.key"},{"id":27,"speaker":1,"speaker_name":"TonyHLP","is_super":1,"belong_class":1,"content":"emmmmm","thread":1,"emoji":0,"img_url":null,"date":1561208435,"type":"text","file_url":null,"file_name":null},{"id":28,"speaker":1,"speaker_name":"TonyHLP","is_super":1,"belong_class":1,"content":"Lorem ipsum dolor sit amet, consectetur adipisicing elit, sed do eiusmod tempor incididunt ut labore et dolore magna aliqua. Ut enim ad minim veniam, quis nostrud exercitation ullamco laboris nisi ut aliquip ex ea commodo consequat. Duis aute irure dolor in reprehenderit in voluptate velit esse cillum dolore eu fugiat nulla pariatur. Excepteur sint occaecat cupidatat non proident, sunt in culpa qui officia deserunt mollit anim id est laborum.","thread":1,"emoji":0,"img_url":null,"date":1561208497,"type":"text","file_url":null,"file_name":null},{"id":29,"speaker":1,"speaker_name":"TonyHLP","is_super":1,"belong_class":1,"content":null,"thread":1,"emoji":0,"img_url":null,"date":1561209034,"type":"file","file_url":"https:\/\/static.ouorz.com\/1561209033941.jpg","file_name":"black-and-white-black-and-white-fog-2237185.jpg"},{"id":30,"speaker":1,"speaker_name":"TonyHLP","is_super":1,"belong_class":1,"content":"Test Image + Text !","thread":1,"emoji":0,"img_url":"https:\/\/static.ouorz.com\/1561209073579.jpg","date":1561209093,"type":"text","file_url":null,"file_name":null},{"id":31,"speaker":1,"speaker_name":"TonyHLP","is_super":1,"belong_class":1,"content":"&lt;h3&gt;Test MarkDown&lt;\/h3&gt;","thread":1,"emoji":0,"img_url":null,"date":1561210687,"type":"text","file_url":null,"file_name":null},{"id":32,"speaker":1,"speaker_name":"TonyHLP","is_super":1,"belong_class":1,"content":"<p>Test Again MarkDown<\/p>\n","thread":1,"emoji":0,"img_url":null,"date":1561211142,"type":"text","file_url":null,"file_name":null},{"id":33,"speaker":1,"speaker_name":"TonyHLP","is_super":1,"belong_class":1,"content":"<h3>Test Again MarkDown<\/h3>\n","thread":1,"emoji":0,"img_url":null,"date":1561211167,"type":"text","file_url":null,"file_name":null},{"id":34,"speaker":3,"speaker_name":"TestTeacher","is_super":1,"belong_class":1,"content":"Hello World","thread":7,"emoji":0,"img_url":null,"date":1561218797,"type":"text","file_url":null,"file_name":null},{"id":35,"speaker":3,"speaker_name":"TestTeacher","is_super":1,"belong_class":1,"content":"Hello Image","thread":7,"emoji":0,"img_url":"https:\/\/static.ouorz.com\/1561218815975.jpg","date":1561218825,"type":"text","file_url":null,"file_name":null},{"id":36,"speaker":3,"speaker_name":"TestTeacher","is_super":1,"belong_class":1,"content":null,"thread":7,"emoji":0,"img_url":null,"date":1561218839,"type":"file","file_url":"https:\/\/static.ouorz.com\/1561218839020.pdf","file_name":"Zeo\u5c0f\u534a _ \u9879\u76ee\u6587\u6848(\u8349\u6848V2.3\uff09.pdf"},{"id":37,"speaker":3,"speaker_name":"TestTeacher","is_super":1,"belong_class":1,"content":null,"thread":7,"emoji":0,"img_url":null,"date":1561219121,"type":"file","file_url":"https:\/\/static.ouorz.com\/1561219119291.zip","file_name":"blog.zip"},{"id":38,"speaker":3,"speaker_name":"TestTeacher","is_super":1,"belong_class":1,"content":null,"thread":7,"emoji":0,"img_url":null,"date":1561219133,"type":"file","file_url":"https:\/\/static.ouorz.com\/1561219133492.jpg","file_name":"13193037-9d060a13a46c233d.jpg"},{"id":39,"speaker":2,"speaker_name":"TonyHe","is_super":0,"belong_class":1,"content":"Pretty Cool!","thread":1,"emoji":0,"img_url":null,"date":1561219271,"type":"text","file_url":null,"file_name":null},{"id":40,"speaker":2,"speaker_name":"TonyHe","is_super":0,"belong_class":1,"content":"<h1>MarkDown<\/h1>\n<h3>Hello MarkDown<\/h3>\n<p>Hello Mark Down Hello Mark Down Hello Mark Down<\/p>\n","thread":1,"emoji":0,"img_url":null,"date":1561219325,"type":"text","file_url":null,"file_name":null}]